---
layout: post
title: Java程序设计环境
abbrlink: 172b6a725dc446408b10f25b147f1442
tags:
  - java
categories:
  - JDK
  - 基础篇
date: 1745339269351
updated: 1746417123576
---

这篇文章介绍了安装 JAVA 幵发工具包的方法，包括下载 JDK、设置环境变量、配置库源文件和文档、自动安装 JDK17 的脚本以及编译并运行 Java 程序。还包括了使用 javap 反编译功能查看 Java 字节码的示例。

<!-- more -->

***

## 安装 Java 幵发工具包

### 下载 JDK

JDK 是 Java Development Kit 的缩写, 下载地址如下

- 可从 [OpenJDK 官网](https://jdk.java.net) 获取对应版本。
- [huaweicloud-openjdk](https://mirrors.huaweicloud.com/openjdk/)
- [huaweicloud-OracleJDK](https://repo.huaweicloud.com/java/jdk/)
- [WEJDK 学习站](https://www.injdk.cn/)

### 设置 JDK

下载 JDK 之后，需要配置环境变量，方便在任何路径下都能识别 java, javac 命令。

- Windows 下最好不要在 JDK 安装路径名中包含空格

  - 我的电脑 --> 环境配置 -> 需要配置 `JAVA_HOME`, `classpath `, `path`

  ```sh
  # 指定 JDK 的安装路径
  JAVA_HOME=C:\Program Files\Java\jdk-17
  PATH=%JAVA_HOME%\bin;%PATH% #
  ```

- 在 Mac 上，运行安装程序。这会把软件安装到 /Library/Java/JavaVirtualMachines/jdk1.8.0\_201.jdk/

  ```sh
  vim ~/.zshrc

  #添加下面的代码
  export JAVA_8_HOME ="$(/usr/libexec/java_home -v 1.8)"
  export JAVA_11_HOME ="$(/usr/libexec/java_home -v 11)"

  #默认设为 JDK1.8
  export JAVA_HOME =$JAVA_8_HOME

  #alias 命令动态切换 JDK 版本
  alias jdk8 =" export JAVA_HOME =$JAVA_8_HOME "
  alias jdk11 =" export JAVA_HOME =$JAVA_11_HOME "
  ```

- 在 Linux 上只需要把 .tar.gz 文件解压缩到你选择的某个位置， 如你的主目录，或者/opt。

  - **用户级配置**（仅对当前用户生效）：`~/.bashrc` 或 `~/.bash_profile`
  - **系统级配置**（对所有用户生效）：`/etc/profile`
  - 编辑 `~/.bashrc` 文件（请将 `/path/to/openjdk-17.0.2` 替换为你实际解压后的路径）：

    ```shell
    mkdir -p /usr/local/java/
    wget https://d6.injdk.cn/openjdk/openjdk/17/openjdk-17.0.1_linux-x64_bin.tar.gz
    tar -xzvf openjdk-17.0.1_linux-x64_bin.tar.gz  -C /usr/local/java/

    export JAVA_HOME=/usr/local/java/openjdk-17.0.2
    export PATH=$PATH:$JAVA_HOME/bin
    # 可选：设置 CLASSPATH（现代 Java 通常不需要）
    export CLASSPATH=.:$JAVA_HOME/lib/dt.jar:$JAVA_HOME/lib/tools.jar

    # 保存文件后，运行以下命令使配置立即生效：
    source ~/.bashrc  # 或 source /etc/profile
    ```

- 保存所做的设置后重新打开终端，验证 java 环境变量是否生效，可以看到版本信息表示安装正常。

  ```ls
  fulsundeMacBook-Pro:~ $ java -version
  java version "1.8.0_201"
  Java(TM) SE Runtime Environment (build 1.8.0_201-b09)
  Java HotSpot(TM) 64-Bit Server VM (build 25.201-b09, mixed mode)
  ```

### 安装库源文件和文档

- 如果你使用的是 OpenJDK 8，源代码通常已包含在安装中, 或从 [OpenJDK 官网](http://jdk.java.net/) 下载特定版本的源码：

  - 在主目录中建立一个目录 javasrc。
  - jdk 目录下找到文件 src.zip。
  - 将 src.zip 文件解压缩到 javasrc 目录。

- Java 8 文档可以单独下载或在线查看：

  - 在线文档：**<https://docs.oracle.com/javase/8/docs/api/>**
  - 本地文档：

    - 可以直接从网站 <http://www.oracle.com/technetwork/java/javase/downloads>
    - 下载 `jdk-8uXXX-docs-all.zip` 并解压, 将 doc 目录重命名为一个更有描述性的名字， 如 javadoc。
    - 在浏览器中导航到 javadoc/api/index.html, 将这个页面增加到书签。

### 脚本-自动安装 JDK17

- 将上述脚本保存为 `install_jdk17.sh`

  ```sh
  #!/bin/bash

  # JDK 自动安装脚本
  # 版本: JDK 17
  # 作者: fulsun
  # 日期: 2025-04-10 00:54:26

  # 定义变量
  JDK_VERSION="17.0.1"
  JDK_URL="https://d.injdk.cn/download/openjdk/17/openjdk-17.0.1_linux-x64_bin.tar.gz"
  INSTALL_DIR="/usr/local/java"
  JAVA_HOME_DIR="/usr/local/jdk-${JDK_VERSION}"
  PROFILE_FILE="/etc/profile"

  # 检查是否以 root 用户运行
  if [ "$(id -u)" != "0" ]; then
      echo "错误: 此脚本必须以root用户身份运行!"
      exit 1
  fi

  # 检查是否已安装 JDK
  check_java_installed() {
      if type -p java &>/dev/null; then
          echo "检测到系统已安装Java:"
          java -version
          echo "是否继续安装JDK 17? (y/n)"
          read answer
          if [ "$answer" != "y" ] && [ "$answer" != "Y" ]; then
              echo "安装已取消。"
              exit 0
          fi
      fi
  }

  # 安装必要的依赖
  install_dependencies() {
      echo "正在安装必要的依赖..."
      if command -v apt-get &>/dev/null; then
          apt-get update
          apt-get install -y wget tar
      elif command -v yum &>/dev/null; then
          yum install -y wget tar
      else
          echo "警告: 无法确定包管理器，跳过依赖安装。"
      fi
  }

  # 下载并安装 JDK
  install_jdk() {
      echo "正在创建安装目录: ${INSTALL_DIR}"
      mkdir -p "${INSTALL_DIR}"

      echo "正在下载JDK ${JDK_VERSION}..."
      if wget "${JDK_URL}" -O /tmp/openjdk-${JDK_VERSION}.tar.gz; then
          echo "下载完成。"
      else
          echo "错误: JDK下载失败!"
          exit 1
      fi

      echo "正在解压JDK到${INSTALL_DIR}..."
      tar -xzf /tmp/openjdk-${JDK_VERSION}.tar.gz -C /usr/local/

      if [ -d "${JAVA_HOME_DIR}" ]; then
          echo "JDK已成功解压到${JAVA_HOME_DIR}"
      else
          echo "错误: JDK解压失败!"
          exit 1
      fi

      # 清理临时文件
      rm -f /tmp/openjdk-${JDK_VERSION}.tar.gz
  }

  # 配置环境变量
  configure_environment() {
      echo "正在配置环境变量..."

      # 检查是否已配置
      if grep -q "JAVA_HOME=${JAVA_HOME_DIR}" "${PROFILE_FILE}"; then
          echo "环境变量已配置，跳过。"
          return
      fi

      cat >> "${PROFILE_FILE}" << EOF

  # Java 环境变量 - 由 JDK 自动安装脚本添加 $(date +%Y-%m-%d)
  export JAVA_HOME=${JAVA_HOME_DIR}
  export JRE_HOME=\${JAVA_HOME}/jre
  export CLASSPATH=.:\${JAVA_HOME}/lib:\${JRE_HOME}/lib
  export PATH=\${JAVA_HOME}/bin:\$PATH
  EOF

      # 使环境变量立即生效
      source "${PROFILE_FILE}"
  }

  # 验证安装
  verify_installation() {
      echo "正在验证JDK安装..."
      if [ -x "${JAVA_HOME_DIR}/bin/java" ]; then
          echo "JDK安装成功!"
          echo "Java版本信息:"
          "${JAVA_HOME_DIR}/bin/java" -version
      else
          echo "错误: JDK安装验证失败!"
          exit 1
      fi
  }

  # 主函数
  main() {
      echo "开始安装JDK ${JDK_VERSION}..."

      check_java_installed
      install_dependencies
      install_jdk
      configure_environment
      verify_installation

      echo "JDK ${JDK_VERSION} 安装完成!"
  }

  # 执行主函数
  main
  ```

- 给脚本添加执行权限：`chmod +x install_jdk17.sh`

- 以 root 用户运行脚本：`sudo ./install_jdk17.sh`

## 编译并运行 Java 程序

- 创建一个简单的 Java 程序文件 `HelloWorld.java`：

  ```java
  public class HelloWorld {
      public static void main(String[] args) {
          System.out.println("Hello, World!");
      }
  }
  ```

- 使用 `javac` 命令编译：编译成功后，会生成 `HelloWorld.class` 字节码文件。

  ```bash
  javac HelloWorld.java
  ```

- 使用 `java` 命令运行编译后的程序：

  ```
  java HelloWorld
  ```

## javap 反编译

- javap 主要用于帮助开发者深入了解 Java 编译器的机制，反编译 Java 代码，查看 Java 字节码

- 用法：`javap <options> <classes>`

- 主要选项有：

  - -version：版本信息
  - -v：输出附加信息
  - -l：输出行号和本地变量表
  - -public：仅显示公共类和成员
  - -protected：显示受保护的/公共类和成员
  - -package：显示程序包/受保护的/公共类和成员 (默认)
  - -p 或-private：显示所有类和成员
  - **-c**：对代码进行反汇编
  - -s：输出内部类型签名
  - -sysinfo：显示正在处理的类的系统信息 (路径, 大小, 日期, MD5 散列)
  - -constants：显示最终常量
  - `-classpath <path>`：指定查找用户类文件的位置
  - `-cp <path>`：指定查找用户类文件的位置
  - `-bootclasspath <path>`：覆盖引导类文件的位置
  - -c：分解方法代码，即显示每个方法具体的字节码
  - -verbose：指定显示更进一步的详细信息

- 除此之外，目前有很多的反编译工具可以用，来查看 Java 编译后的代码

  - **JD-GUI：** 一个用 C++ 开发的 Java 反编译工具

### 示例 1

- 代码

  ```java
  class TestJavap{
  	public static void main(String[] args){
  		int i=3;
          i++;
  		String name = "lily";
  	}
  }
  ```

- 反编译

  ```java
  javap -c TestJavap
  Compiled from "TestJavap.java"
  class TestJavap {
    TestJavap();
      Code:
         0: aload_0
         1: invokespecial #1                  // Method java/lang/Object."<init>":()V
         4: return

    public static void main(java.lang.String[]);
      Code:
         0: iconst_3	//常量 0 压入操作数栈
         1: istore_1	//把栈顶的值放到局部变量 1 中，即 i 中
         //这个个指令，把局部变量 1，也就是 i，增加 1，这个指令不会导致栈的变化，i 此时变成 4 了
         2: iinc          1, 1
         5: ldc           #7                  // String lily
         7: astore_2
         8: return
  }

  ```

### 示例 2

- 代码

  ```java
  public static int add(int a,int b){
      int c=0;
      c=a+b;
      return c;
  }
  ```

- 反编译 `Desktop>javap -c TestJavap`

  - 局部变量表 index 是从 0 开始

  ```java
  0: iconst_0        //常量 0 压入操作数栈
  1: istore_2        //弹出操作数栈栈顶元素，保存到局部变量表第 2 个位置
  2: iload_0         //第 0 个变量压入操作数栈
  3: iload_1         //第 1 个变量压入操作数栈
  4: iadd            //操作数栈中的前两个 int 相加，并将结果压入操作数栈顶
  5: istore_2        //弹出操作数栈栈顶元素，保存到局部变量表第 2 个位置
  6: iload_2         //加载局部变量表的第 2 个变量到操作数栈顶
  7: ireturn         //返回
  ```
